eDOCr/keras_ocr/__init__.py
eDOCr/keras_ocr/config.py
eDOCr/keras_ocr/data_generation.py
eDOCr/keras_ocr/datasets.py
eDOCr/keras_ocr/detection.py
eDOCr/keras_ocr/evaluation.py
eDOCr/keras_ocr/pipeline.py
eDOCr/keras_ocr/recognition.py
eDOCr/keras_ocr/tools.py
eDOCr/keras_ocr_models/__init__.py
eDOCr/keras_ocr_models/train_recognizer.py
eDOCr_javvi51-0.0.1.dist-info/LICENSE
eDOCr_javvi51-0.0.1.dist-info/METADATA
eDOCr_javvi51-0.0.1.dist-info/WHEEL
eDOCr_javvi51-0.0.1.dist-info/top_level.txt
eDOCr_javvi51-0.0.1.dist-info/RECORD
