Metadata-Version: 2.1
Name: eDOCr-javvi51
Version: 0.0.1
Summary: OCR for Engineering Mechanical Drawings
Author: eDOCr
Project-URL: Homepage, https://github.com/javvi51/eDOCr
Project-URL: Bug Tracker, https://github.com/javvi51/eDOCr/issues
Classifier: Programming Language :: Python :: 3
Classifier: License :: OSI Approved :: MIT License
Classifier: Operating System :: OS Independent
Requires-Python: >=3.7
License-File: LICENSE
